{
  "id": "port/20",
  "family": "port",
  "slug": "20",
  "title": "Port 20 — ftp-data",
  "summary": "Well-known port 20 (tcp/udp/sctp): File Transfer [Default Data]. Service name: ftp-data. Referenced in RFC9260.",
  "kind": "port",
  "status": "standard",
  "verification": "verified",
  "tier": "A",
  "source_url": "https://www.iana.org/assignments/service-names-port-numbers/service-names-port-numbers.csv",
  "source_version": "IANA registry, Last-Modified: Fri, 29 May 2026 01:11:28 GMT",
  "retrieved_date": "2026-05-29",
  "ext_type": "iana-registry-row@1",
  "ext": {
    "value": 20,
    "reference_rfcs": [
      "RFC9260"
    ],
    "transports": [
      "tcp",
      "udp",
      "sctp"
    ],
    "raw_columns": {
      "Service Name": "ftp-data",
      "Port Number": "20",
      "Transport Protocol": "tcp",
      "Description": "File Transfer [Default Data]",
      "Assignee": "[Jon_Postel]",
      "Contact": "[Jon_Postel]",
      "Registration Date": "",
      "Modification Date": "",
      "Reference": "",
      "Service Code": "",
      "Unauthorized Use Reported": "",
      "Assignment Notes": ""
    }
  },
  "updated": "2026-05-29"
}
