{
  "id": "port/693",
  "family": "port",
  "slug": "693",
  "title": "Port 693 — connendp",
  "summary": "Well-known port 693 (tcp/udp): almanid Connection Endpoint. Service name: connendp.",
  "kind": "port",
  "status": "standard",
  "verification": "verified",
  "tier": "A",
  "source_url": "https://www.iana.org/assignments/service-names-port-numbers/service-names-port-numbers.csv",
  "source_version": "IANA registry, Last-Modified: Fri, 29 May 2026 01:11:28 GMT",
  "retrieved_date": "2026-05-29",
  "ext_type": "iana-registry-row@1",
  "ext": {
    "value": 693,
    "reference_rfcs": [],
    "transports": [
      "tcp",
      "udp"
    ],
    "raw_columns": {
      "Service Name": "connendp",
      "Port Number": "693",
      "Transport Protocol": "tcp",
      "Description": "almanid Connection Endpoint",
      "Assignee": "[Ronny_Bremer]",
      "Contact": "[Ronny_Bremer]",
      "Registration Date": "",
      "Modification Date": "",
      "Reference": "",
      "Service Code": "",
      "Unauthorized Use Reported": "",
      "Assignment Notes": ""
    }
  },
  "updated": "2026-05-29"
}
