{
  "id": "cbor-tag/1701996915",
  "family": "cbor-tag",
  "slug": "1701996915",
  "title": "CBOR tag 1701996915 — Array of content-addressed blocks and ERIS read capabilities",
  "summary": "CBOR tag 1701996915 (data item: array): Array of content-addressed blocks and ERIS read capabilities.",
  "kind": "tag",
  "status": "standard",
  "verification": "verified",
  "tier": "A",
  "source_url": "https://www.iana.org/assignments/cbor-tags/tags.csv",
  "source_version": "IANA registry, Last-Modified: Thu, 02 Apr 2026 23:51:20 GMT",
  "retrieved_date": "2026-05-29",
  "ext_type": "iana-registry-row@1",
  "ext": {
    "value": 1701996915,
    "reference_rfcs": [],
    "raw_columns": {
      "Tag": "1701996915",
      "Data Item": "array",
      "Semantics": "Array of content-addressed blocks and ERIS read capabilities",
      "Reference": "[Endo_Renberg]",
      "Template": "template/1701996915"
    }
  },
  "updated": "2026-05-29"
}
