{
  "id": "media-type/audio-vnd-digital-winds",
  "family": "media-type",
  "slug": "audio-vnd-digital-winds",
  "title": "audio/vnd.digital-winds",
  "summary": "Media type \"audio/vnd.digital-winds\".",
  "kind": "media-type",
  "status": "standard",
  "verification": "verified",
  "tier": "A",
  "source_url": "https://www.iana.org/assignments/media-types/audio.csv",
  "source_version": "IANA registry, Last-Modified: Fri, 06 Feb 2026 00:26:24 GMT",
  "retrieved_date": "2026-05-29",
  "ext_type": "iana-registry-row@1",
  "ext": {
    "value": "audio/vnd.digital-winds",
    "reference_rfcs": [],
    "raw_columns": {
      "Name": "vnd.digital-winds",
      "Template": "audio/vnd.digital-winds",
      "Reference": "[Armands_Strazds]"
    }
  },
  "updated": "2026-05-29",
  "aliases": [
    "audio/vnd.digital-winds"
  ]
}
