{
  "id": "media-type/image-avif",
  "family": "media-type",
  "slug": "image-avif",
  "title": "image/avif",
  "summary": "Media type \"image/avif\".",
  "kind": "media-type",
  "status": "standard",
  "verification": "verified",
  "tier": "A",
  "source_url": "https://www.iana.org/assignments/media-types/image.csv",
  "source_version": "IANA registry, Last-Modified: Thu, 16 Apr 2026 01:41:21 GMT",
  "retrieved_date": "2026-05-29",
  "ext_type": "iana-registry-row@1",
  "ext": {
    "value": "image/avif",
    "reference_rfcs": [],
    "raw_columns": {
      "Name": "avif",
      "Template": "image/avif",
      "Reference": "[Alliance_for_Open_Media][Cyril_Concolato]"
    }
  },
  "updated": "2026-05-29",
  "aliases": [
    "image/avif"
  ]
}
