{
  "id": "media-type/video-lottie-json",
  "family": "media-type",
  "slug": "video-lottie-json",
  "title": "video/lottie+json",
  "summary": "Media type \"video/lottie+json\".",
  "kind": "media-type",
  "status": "standard",
  "verification": "verified",
  "tier": "A",
  "source_url": "https://www.iana.org/assignments/media-types/video.csv",
  "source_version": "IANA registry, Last-Modified: Tue, 23 Sep 2025 00:51:18 GMT",
  "retrieved_date": "2026-05-29",
  "ext_type": "iana-registry-row@1",
  "ext": {
    "value": "video/lottie+json",
    "reference_rfcs": [],
    "raw_columns": {
      "Name": "lottie+json",
      "Template": "video/lottie+json",
      "Reference": "[Lottie_Animation_Community]"
    }
  },
  "updated": "2026-05-29",
  "aliases": [
    "video/lottie+json"
  ]
}
